MANIFEST.in
README.md
build.py
pyproject.toml
requirements-dev.txt
requirements.txt
setup.py
polygeom/__init__.py
polygeom/entity.py
polygeom/point.py
polygeom/polygon.py
polygeom/utils.py
polygeom/vector.py
polygeom.egg-info/PKG-INFO
polygeom.egg-info/SOURCES.txt
polygeom.egg-info/dependency_links.txt
polygeom.egg-info/requires.txt
polygeom.egg-info/top_level.txt